Kookbook.py
MANIFEST
MANIFEST.in
README.html
README.rst
benchmarker.py
setup.py
style.css
Benchmarker.egg-info/PKG-INFO
Benchmarker.egg-info/SOURCES.txt
Benchmarker.egg-info/dependency_links.txt
Benchmarker.egg-info/top_level.txt
examples/bench_strconcat.py
test/benchmarker_test.py
test/oktest.py